arraybridge/__init__.py
arraybridge/converters.py
arraybridge/converters_registry.py
arraybridge/decorators.py
arraybridge/dtype_scaling.py
arraybridge/exceptions.py
arraybridge/framework_config.py
arraybridge/framework_ops.py
arraybridge/gpu_cleanup.py
arraybridge/oom_recovery.py
arraybridge/slice_processing.py
arraybridge/stack_utils.py
arraybridge/types.py
arraybridge/utils.py
arraybridge-0.2.9.dist-info/METADATA
arraybridge-0.2.9.dist-info/WHEEL
arraybridge-0.2.9.dist-info/licenses/LICENSE
arraybridge-0.2.9.dist-info/RECORD
