Metadata-Version: 2.4
Name: arraybridge
Version: 0.2.9
Summary: Unified API for NumPy, CuPy, PyTorch, TensorFlow, JAX, and pyclesperanto with automatic memory type conversion
Project-URL: Homepage, https://github.com/OpenHCSDev/arraybridge
Project-URL: Documentation, https://arraybridge.readthedocs.io
Project-URL: Repository, https://github.com/OpenHCSDev/arraybridge
Project-URL: Issues, https://github.com/OpenHCSDev/arraybridge/issues
Author-email: Tristan Simas <tristan.simas@mail.mcgill.ca>
License: MIT
License-File: LICENSE
Keywords: array,conversion,cupy,gpu,jax,numpy,pytorch,tensor,tensorflow
Classifier: Development Status :: 4 - Beta
Classifier: Intended Audience :: Developers
Classifier: Intended Audience :: Science/Research
Classifier: License :: OSI Approved :: MIT License
Classifier: Programming Language :: Python :: 3
Classifier: Programming Language :: Python :: 3.9
Classifier: Programming Language :: Python :: 3.10
Classifier: Programming Language :: Python :: 3.11
Classifier: Programming Language :: Python :: 3.12
Classifier: Topic :: Scientific/Engineering
Classifier: Topic :: Software Development :: Libraries :: Python Modules
Requires-Python: >=3.9
Requires-Dist: metaclass-registry
Requires-Dist: numpy>=1.20
Provides-Extra: all
Requires-Dist: cupy>=10.0; extra == 'all'
Requires-Dist: jax>=0.3; extra == 'all'
Requires-Dist: jaxlib>=0.3; extra == 'all'
Requires-Dist: pyclesperanto>=0.10; extra == 'all'
Requires-Dist: tensorflow>=2.8; extra == 'all'
Requires-Dist: torch>=1.10; extra == 'all'
Provides-Extra: cupy
Requires-Dist: cupy>=10.0; extra == 'cupy'
Provides-Extra: dev
Requires-Dist: black>=23.0; extra == 'dev'
Requires-Dist: mypy>=1.0; extra == 'dev'
Requires-Dist: pytest-cov>=4.0; extra == 'dev'
Requires-Dist: pytest>=7.0; extra == 'dev'
Requires-Dist: ruff>=0.1.0; extra == 'dev'
Provides-Extra: docs
Requires-Dist: sphinx-autodoc-typehints>=1.25; extra == 'docs'
Requires-Dist: sphinx-rtd-theme>=2.0; extra == 'docs'
Requires-Dist: sphinx>=7.0; extra == 'docs'
Provides-Extra: gpu
Requires-Dist: cucim-cu12<26.0.0,>=25.6.0; extra == 'gpu'
Requires-Dist: cupy-cuda12x<14.0.0,>=13.3.0; extra == 'gpu'
Requires-Dist: jax-cuda12-pjrt<0.6.0,>=0.5.3; extra == 'gpu'
Requires-Dist: jax-cuda12-plugin<0.6.0,>=0.5.3; extra == 'gpu'
Requires-Dist: jax<0.6.0,>=0.5.3; extra == 'gpu'
Requires-Dist: jaxlib<0.6.0,>=0.5.3; extra == 'gpu'
Requires-Dist: pyclesperanto>=0.17.1; extra == 'gpu'
Requires-Dist: tensorflow-probability[tf]<0.26.0,>=0.25.0; extra == 'gpu'
Requires-Dist: tensorflow<2.20.0,>=2.19.0; extra == 'gpu'
Requires-Dist: torch<2.8.0,>=2.6.0; extra == 'gpu'
Requires-Dist: torchvision<0.23.0,>=0.21.0; extra == 'gpu'
Provides-Extra: jax
Requires-Dist: jax>=0.3; extra == 'jax'
Requires-Dist: jaxlib>=0.3; extra == 'jax'
Provides-Extra: pyclesperanto
Requires-Dist: pyclesperanto>=0.10; extra == 'pyclesperanto'
Provides-Extra: tensorflow
Requires-Dist: tensorflow>=2.8; extra == 'tensorflow'
Provides-Extra: torch
Requires-Dist: torch>=1.10; extra == 'torch'
